bifrostlib/__init__.py
bifrostlib/common.py
bifrostlib/database_interface.py
bifrostlib/datahandling.py
bifrostlib/schemas/bifrost.jsonc
bifrostlib-2.1.18.dist-info/LICENSE
bifrostlib-2.1.18.dist-info/METADATA
bifrostlib-2.1.18.dist-info/WHEEL
bifrostlib-2.1.18.dist-info/top_level.txt
bifrostlib-2.1.18.dist-info/RECORD
