Metadata-Version: 2.1
Name: bifrostlib
Version: 2.1.18
Summary: Datahandling functions for bifrost (later to be API interface)
Home-page: https://github.com/ssi-dk/bifrostlib
Author: Kim Ng, Martin Basterrechea
Author-email: kimn@ssi.dk
License: UNKNOWN
Platform: UNKNOWN
Requires-Dist: pymongo
Requires-Dist: python-magic
Requires-Dist: dnspython
Requires-Dist: jsmin
Requires-Dist: warlock
Requires-Dist: pandas
Requires-Dist: libmagic
